lytomo_watershed/__init__.py
lytomo_watershed/descendant.py
lytomo_watershed/fgpa.py
lytomo_watershed/get_data.py
lytomo_watershed/get_density_field.py
lytomo_watershed/halos.py
lytomo_watershed/latis.py
lytomo_watershed/load_data.py
lytomo_watershed/minima.py
lytomo_watershed/mpi4py_helper.py
lytomo_watershed/paint_map.py
lytomo_watershed/plot_simulation.py
lytomo_watershed/progenitor_particles.py
lytomo_watershed/spectra_mocking.py
lytomo_watershed/z_bin.py
lytomo_watershed/illustris_python/__init__.py
lytomo_watershed/illustris_python/groupcat.py
lytomo_watershed/illustris_python/lhalotree.py
lytomo_watershed/illustris_python/snapshot.py
lytomo_watershed/illustris_python/sublink.py
lytomo_watershed/illustris_python/util.py
lytomo_watershed/illustris_python/tests/__init__.py
lytomo_watershed/illustris_python/tests/__main__.py
lytomo_watershed/illustris_python/tests/groupcat_test.py
lytomo_watershed/illustris_python/tests/snapshot_test.py
lytomo_watershed/illustris_python/tests/sublink_test.py
lytomo_watershed-0.3.0.dist-info/LICENSE
lytomo_watershed-0.3.0.dist-info/METADATA
lytomo_watershed-0.3.0.dist-info/WHEEL
lytomo_watershed-0.3.0.dist-info/top_level.txt
lytomo_watershed-0.3.0.dist-info/RECORD
