Metadata-Version: 2.1
Name: lytomo-watershed
Version: 0.3.0
Summary: Detection of protoclusters in Ly-alpha tomography surveys
Home-page: https://github.com/mahdiqezlou/LyTomo_Watershed
Author: Mahdi Qezlou, Drew Newman, Gwen Rudie, Simeon Bird
Author-email: mahdi.qezlou@email.ucr.edu
License: UNKNOWN
Project-URL: Bug Tracker, https://github.com/mahdiqezlou/LyTomo_Watershed
Platform: UNKNOWN
Classifier: Programming Language :: Python :: 3
Classifier: License :: OSI Approved :: MIT License
Classifier: Operating System :: OS Independent
Requires-Python: >=3.6
License-File: LICENSE
